wechat_user/__init__.py
wechat_user/admin.py
wechat_user/apps.py
wechat_user/jwt_auth.py
wechat_user/models.py
wechat_user/serializers.py
wechat_user/services.py
wechat_user/signals.py
wechat_user/sms_utils.py
wechat_user/tests.py
wechat_user/urls.py
wechat_user/views.py
wechat_user/migrations/0001_initial.py
wechat_user/migrations/0002_user_status.py
wechat_user/migrations/0003_userwxacode.py
wechat_user/migrations/0004_auto_20181220_1431.py
wechat_user/migrations/__init__.py
django_wechat_user-0.80.dist-info/LICENSE
django_wechat_user-0.80.dist-info/METADATA
django_wechat_user-0.80.dist-info/WHEEL
django_wechat_user-0.80.dist-info/top_level.txt
django_wechat_user-0.80.dist-info/RECORD
