Metadata-Version: 2.1
Name: django-wechat-user
Version: 0.80
Summary: A wechat user model
Home-page: UNKNOWN
Author: Ken Zhang
Author-email: kennir@gmail.com
License: BSD License
Platform: UNKNOWN
Classifier: Environment :: Web Environment
Classifier: Framework :: Django
Classifier: Framework :: Django :: 2.1
Classifier: Intended Audience :: Developers
Classifier: License :: OSI Approved :: BSD License
Classifier: Operating System :: OS Independent
Classifier: Programming Language :: Python
Classifier: Programming Language :: Python :: 3.5
Classifier: Programming Language :: Python :: 3.6
Classifier: Topic :: Internet :: WWW/HTTP
Classifier: Topic :: Internet :: WWW/HTTP :: Dynamic Content
Requires-Dist: aliyun-python-sdk-core-v3 (==2.9.4)
Requires-Dist: aliyun-python-sdk-dysmsapi (==1.0.0)
Requires-Dist: appdirs
Requires-Dist: arrow
Requires-Dist: astroid
Requires-Dist: attrs
Requires-Dist: certifi
Requires-Dist: chardet
Requires-Dist: Click
Requires-Dist: Django
Requires-Dist: django-cors-headers
Requires-Dist: django-redis
Requires-Dist: django-reset-migrations
Requires-Dist: djangorestframework
Requires-Dist: idna
Requires-Dist: isort
Requires-Dist: lazy-object-proxy
Requires-Dist: mccabe
Requires-Dist: pep8
Requires-Dist: pycryptodome
Requires-Dist: PyJWT
Requires-Dist: pylint
Requires-Dist: python-dateutil
Requires-Dist: pytz
Requires-Dist: redis
Requires-Dist: requests
Requires-Dist: rope
Requires-Dist: six
Requires-Dist: toml
Requires-Dist: typed-ast
Requires-Dist: urllib3
Requires-Dist: wrapt
